requestyai/__init__.py
requestyai/ainsights/__init__.py
requestyai/ainsights/client.py
requestyai/ainsights/error.py
requestyai/ainsights/types/__init__.py
requestyai/ainsights/types/event.py
requestyai/http/async_client.py
requestyai/http/atomic.py
requestyai/http/retry_jitter_type.py
requestyai/http/retry_policy.py
requestyai/http/retry_transport.py
requestyai-0.3.5.dist-info/LICENSE
requestyai-0.3.5.dist-info/METADATA
requestyai-0.3.5.dist-info/WHEEL
requestyai-0.3.5.dist-info/RECORD
