Metadata-Version: 2.1
Name: requestyai
Version: 0.3.5
Summary: Deliver AI products in days, not months, using requesty.ai
License: License :: OSI Approved :: Apache Software License
Author: RequestyAI
Author-email: support@requesty.ai
Requires-Python: >=3.9
Classifier: Intended Audience :: Developers
Classifier: License :: OSI Approved :: Apache Software License
Classifier: License :: Other/Proprietary License
Classifier: Operating System :: MacOS
Classifier: Operating System :: Microsoft :: Windows
Classifier: Operating System :: OS Independent
Classifier: Operating System :: POSIX
Classifier: Operating System :: POSIX :: Linux
Classifier: Programming Language :: Python :: 3
Classifier: Programming Language :: Python :: 3.9
Classifier: Programming Language :: Python :: 3.10
Classifier: Programming Language :: Python :: 3.11
Classifier: Programming Language :: Python :: 3.12
Classifier: Programming Language :: Python :: 3.13
Classifier: Topic :: Software Development :: Libraries :: Python Modules
Classifier: Typing :: Typed
Requires-Dist: httpx (>=0.25.2,<0.26.0)
Requires-Dist: openai (>=1.54.4,<2.0.0)
Requires-Dist: pydantic (>=2.9.2,<3.0.0)
